fib/__init__.py
fib/fib.py
fib/main.py
fib/parallelization.py
fib/parser.py
fibonacci_number-0.0.1.dist-info/licenses/LICENSE
fibonacci_number-0.0.1.dist-info/METADATA
fibonacci_number-0.0.1.dist-info/WHEEL
fibonacci_number-0.0.1.dist-info/entry_points.txt
fibonacci_number-0.0.1.dist-info/top_level.txt
fibonacci_number-0.0.1.dist-info/RECORD
