Metadata-Version: 2.4
Name: fibonacci_number
Version: 0.0.1
Summary: Project about Fibonacci algorithms, including multiple parallelization strategies.
Author-email: "v-m.dev" <v.mdeve.ops@gmail.com>
License-Expression: MIT
Project-URL: Homepage, https://github.com/v-mdev/fibonacci_project
Project-URL: Issues, https://github.com/v-mdev/fibonacci_project/issues
Classifier: Programming Language :: Python :: 3
Classifier: Operating System :: OS Independent
Classifier: Topic :: Software Development
Requires-Python: >=3.10
License-File: LICENSE
Requires-Dist: numpy>=2.2.6
Requires-Dist: typer>=0.15.4
Provides-Extra: dev
Requires-Dist: ruff>=0.11.6; extra == "dev"
Requires-Dist: pytest>=8.3.5; extra == "dev"
Dynamic: license-file
